rchitect/__init__.py
rchitect/_cffi.abi3.so
rchitect/build.py
rchitect/callbacks.py
rchitect/completion.py
rchitect/console.py
rchitect/dispatch.py
rchitect/interface.py
rchitect/py_tools.py
rchitect/repl.py
rchitect/setup.py
rchitect/types.py
rchitect/utils.py
rchitect/xptr.py
rchitect/_cffi/R.h
rchitect/_cffi/gil.c
rchitect/_cffi/gil.h
rchitect/_cffi/libR.c
rchitect/_cffi/libR.h
rchitect/_cffi/parse.c
rchitect/_cffi/parse.h
rchitect/_cffi/process_events.c
rchitect/_cffi/process_events.h
rchitect/reticulate/__init__.py
rchitect/reticulate/config.R
rchitect/reticulate/path.py
rchitect/reticulate/py_config.py
rchitect-0.4.9.dist-info/METADATA
rchitect-0.4.9.dist-info/WHEEL
rchitect-0.4.9.dist-info/top_level.txt
rchitect-0.4.9.dist-info/RECORD
rchitect-0.4.9.dist-info/licenses/LICENSE
