Metadata-Version: 2.1
Name: rchitect
Version: 0.4.9
Summary: Mapping R API to Python
Author-email: Randy Lai <randy.cs.lai@gmail.com>
License: The MIT License (MIT)
Project-URL: Homepage, https://github.com/randy3k/rchitect
Requires-Python: >=3.7
License-File: LICENSE
Requires-Dist: cffi>=1.10.0
Requires-Dist: packaging>=23.0
Provides-Extra: dev
Requires-Dist: pytest; extra == "dev"
Requires-Dist: pytest-mock; extra == "dev"
Requires-Dist: pytest-cov; extra == "dev"
